proofscape/__init__.py
proofscape-0.0.1.dist-info/LICENSE
proofscape-0.0.1.dist-info/METADATA
proofscape-0.0.1.dist-info/WHEEL
proofscape-0.0.1.dist-info/top_level.txt
proofscape-0.0.1.dist-info/RECORD
